poly_readme/__init__.py
poly_readme/cli.py
poly_readme-0.1.0.dist-info/LICENSE
poly_readme-0.1.0.dist-info/METADATA
poly_readme-0.1.0.dist-info/WHEEL
poly_readme-0.1.0.dist-info/entry_points.txt
poly_readme-0.1.0.dist-info/top_level.txt
poly_readme-0.1.0.dist-info/RECORD
