Metadata-Version: 2.1
Name: poly-readme
Version: 0.1.0
Summary: A tool to translate README files into multiple languages using ChatGPT.
Home-page: https://github.com/drllr/poly-readme
Author: Chad Lee
Author-email: think.bicycle@gmail.com
License: MIT
Classifier: Programming Language :: Python :: 3
Classifier: License :: OSI Approved :: MIT License
Classifier: Operating System :: OS Independent
Requires-Python: >=3.7
License-File: LICENSE
Requires-Dist: openai>=1.0.0
Requires-Dist: questionary>=1.10.0
Requires-Dist: keyring>=24.0.0
Requires-Dist: PyYAML>=6.0.0
